[
  {
    "full_name": "Cefalo/quick-meet",
    "stargazers_count": 32,
    "open_issues_count": 18,
    "forks_count": 21
  },
  {
    "full_name": "mutasim77/design-patterns",
    "stargazers_count": 120,
    "open_issues_count": 3,
    "forks_count": 14
  },
  {
    "full_name": "khoj-ai/khoj",
    "stargazers_count": 29880,
    "open_issues_count": 75,
    "forks_count": 1664
  },
  {
    "full_name": "practical-tutorials/project-based-learning",
    "stargazers_count": 226336,
    "open_issues_count": 221,
    "forks_count": 29574
  },
  {
    "full_name": "aniruddha-adhikary/mrt-buddy",
    "stargazers_count": 360,
    "open_issues_count": 20,
    "forks_count": 104
  },
  {
    "full_name": "reduxjs/redux-templates",
    "stargazers_count": 1467,
    "open_issues_count": 13,
    "forks_count": 272
  },
  {
    "full_name": "aulipriya/video-image-converter",
    "stargazers_count": 2,
    "open_issues_count": 0,
    "forks_count": 0
  },
  {
    "full_name": "sudheerj/reactjs-interview-questions",
    "stargazers_count": 41880,
    "open_issues_count": 14,
    "forks_count": 9854
  },
  {
    "full_name": "jeebon/cefcom-node-angular",
    "stargazers_count": 3,
    "open_issues_count": 4,
    "forks_count": 0
  },
  {
    "full_name": "ByteByteGoHq/system-design-101",
    "stargazers_count": 71963,
    "open_issues_count": 45,
    "forks_count": 7652
  },
  {
    "full_name": "ripienaar/free-for-dev",
    "stargazers_count": 95105,
    "open_issues_count": 12,
    "forks_count": 10284
  },
  {
    "full_name": "sindresorhus/awesome",
    "stargazers_count": 358520,
    "open_issues_count": 56,
    "forks_count": 29014
  },
  {
    "full_name": "foyzulkarim/mock-interviews-2023",
    "stargazers_count": 40,
    "open_issues_count": 0,
    "forks_count": 9
  },
  {
    "full_name": "mertturkmenoglu/typescript-dependency-injection",
    "stargazers_count": 44,
    "open_issues_count": 1,
    "forks_count": 17
  },
  {
    "full_name": "mtdvio/every-programmer-should-know",
    "stargazers_count": 86998,
    "open_issues_count": 54,
    "forks_count": 8003
  },
  {
    "full_name": "donnemartin/system-design-primer",
    "stargazers_count": 297683,
    "open_issues_count": 490,
    "forks_count": 49477
  },
  {
    "full_name": "bregman-arie/devops-exercises",
    "stargazers_count": 75513,
    "open_issues_count": 35,
    "forks_count": 16806
  },
  {
    "full_name": "simantaturja/Learn-Java-Spring",
    "stargazers_count": 132,
    "open_issues_count": 0,
    "forks_count": 77
  },
  {
    "full_name": "ikatyang/emoji-cheat-sheet",
    "stargazers_count": 13032,
    "open_issues_count": 67,
    "forks_count": 4525
  },
  {
    "full_name": "lahin31/system-design-bangla",
    "stargazers_count": 1000,
    "open_issues_count": 1,
    "forks_count": 403
  },
  {
    "full_name": "kamranahmedse/developer-roadmap",
    "stargazers_count": 316945,
    "open_issues_count": 226,
    "forks_count": 41124
  },
  {
    "full_name": "confluentinc/cp-all-in-one",
    "stargazers_count": 1033,
    "open_issues_count": 41,
    "forks_count": 692
  },
  {
    "full_name": "prometheus-operator/prometheus-operator",
    "stargazers_count": 9412,
    "open_issues_count": 231,
    "forks_count": 3765
  },
  {
    "full_name": "kubeshop/botkube",
    "stargazers_count": 2208,
    "open_issues_count": 56,
    "forks_count": 295
  },
  {
    "full_name": "emojicode/emojicode",
    "stargazers_count": 3354,
    "open_issues_count": 21,
    "forks_count": 163
  },
  {
    "full_name": "prometheus/graphite_exporter",
    "stargazers_count": 367,
    "open_issues_count": 21,
    "forks_count": 105
  },
  {
    "full_name": "noman13/oj-solutions",
    "stargazers_count": 1,
    "open_issues_count": 0,
    "forks_count": 0
  },
  {
    "full_name": "learning-zone/nodejs-basics",
    "stargazers_count": 3108,
    "open_issues_count": 0,
    "forks_count": 1038
  },
  {
    "full_name": "Shahriar220/GithubUserFinder",
    "stargazers_count": 12,
    "open_issues_count": 0,
    "forks_count": 0
  },
  {
    "full_name": "AbdullahAlShaad/bookstore-api-server",
    "stargazers_count": 23,
    "open_issues_count": 0,
    "forks_count": 0
  }
]